cdk_lambda_alias_retention/__init__.py
cdk_lambda_alias_retention/py.typed
cdk_lambda_alias_retention/_jsii/__init__.py
cdk_lambda_alias_retention/_jsii/cdk-lambda-alias-retention@2.1.2.jsii.tgz
cdk_lambda_alias_retention-2.1.2.dist-info/LICENSE
cdk_lambda_alias_retention-2.1.2.dist-info/METADATA
cdk_lambda_alias_retention-2.1.2.dist-info/WHEEL
cdk_lambda_alias_retention-2.1.2.dist-info/top_level.txt
cdk_lambda_alias_retention-2.1.2.dist-info/RECORD
