Metadata-Version: 2.1
Name: cdk-lambda-alias-retention
Version: 2.1.2
Summary: cdk-lambda-alias-retention
Home-page: https://github.com/kimisme9386/cdk-lambda-alias-retention.git
Author: Chris Yang<kimisme9386@gmail.com>
License: Apache-2.0
Project-URL: Source, https://github.com/kimisme9386/cdk-lambda-alias-retention.git
Platform: UNKNOWN
Classifier: Intended Audience :: Developers
Classifier: Operating System :: OS Independent
Classifier: Programming Language :: JavaScript
Classifier: Programming Language :: Python :: 3 :: Only
Classifier: Programming Language :: Python :: 3.6
Classifier: Programming Language :: Python :: 3.7
Classifier: Programming Language :: Python :: 3.8
Classifier: Programming Language :: Python :: 3.9
Classifier: Typing :: Typed
Classifier: Development Status :: 5 - Production/Stable
Classifier: License :: OSI Approved
Requires-Python: >=3.6
License-File: LICENSE
Requires-Dist: aws-cdk-lib (<3.0.0,>=2.1.0)
Requires-Dist: constructs (<11.0.0,>=10.0.5)
Requires-Dist: jsii (<2.0.0,>=1.49.0)
Requires-Dist: publication (>=0.0.3)
